ct_redis_cache_lib/__init__.py
ct_redis_cache_lib/cache.py
ct_redis_cache_lib-0.0.2.dist-info/METADATA
ct_redis_cache_lib-0.0.2.dist-info/WHEEL
ct_redis_cache_lib-0.0.2.dist-info/top_level.txt
ct_redis_cache_lib-0.0.2.dist-info/RECORD
